logtopg/__init__.py
logtopg/createtable.sql
logtopg/insertrow.sql
logtopg/version.py
logtopg/tests/__init__.py
logtopg/tests/test_logtopg.py
logtopg-1.0.2.dist-info/METADATA
logtopg-1.0.2.dist-info/WHEEL
logtopg-1.0.2.dist-info/top_level.txt
logtopg-1.0.2.dist-info/RECORD
