Metadata-Version: 2.4
Name: logtopg
Version: 1.0.2
Summary: Python logging handler that stores logs in postgresql
Home-page: https://github.com/216software/logtopg/
Author: 216 Software, LLC
Author-email: info@216software.com
License: BSD License
Requires-Dist: psycopg2
Dynamic: author
Dynamic: author-email
Dynamic: home-page
Dynamic: license
Dynamic: requires-dist
Dynamic: summary
